aiida_fenics/__init__.py
aiida_fenics/calculation/__init__.py
aiida_fenics/calculation/pfdisloc.py
aiida_fenics/cli/__init__.py
aiida_fenics/data/__init__.py
aiida_fenics/parsers/__init__.py
aiida_fenics/parsers/pfdisloc.py
aiida_fenics/workflows/__init__.py
aiida_fenics-0.1.0.dist-info/AUTHORS
aiida_fenics-0.1.0.dist-info/LICENSE
aiida_fenics-0.1.0.dist-info/METADATA
aiida_fenics-0.1.0.dist-info/WHEEL
aiida_fenics-0.1.0.dist-info/entry_points.txt
aiida_fenics-0.1.0.dist-info/top_level.txt
aiida_fenics-0.1.0.dist-info/RECORD
