Metadata-Version: 2.1
Name: aiida-fenics
Version: 0.1.0
Summary: Python package containing an AiiDA Plugin for running the pfdisloc-code (phasefield dislocation interaction) from the IAS-9 of the Forschungszentrum Juelich GmbH. The code is based on Fenics. The package also contains some workflows and utility
Home-page: https://github.com/Materials-Data-Science-and-Informatics/aiida-fenics
Author: Forschungszentrum Juelich GmbH (IAS-9)
Author-email: j.broeder@fz-juelich.de
License: MIT License, see LICENSE.txt file.
Keywords: pfdisloc aiida workflows dislocation phasefield phasefield-dislocation-interaction fenics FEM juelich dft FZJ ias-9
Platform: UNKNOWN
Classifier: Framework :: AiiDA
Classifier: License :: OSI Approved :: MIT License
Classifier: Operating System :: POSIX :: Linux
Classifier: Operating System :: MacOS :: MacOS X
Classifier: Programming Language :: Python :: 3
Classifier: Programming Language :: Python :: 3.6
Classifier: Programming Language :: Python :: 3.7
Classifier: Programming Language :: Python :: 3.8
Classifier: Programming Language :: Python :: 3.9
Classifier: Environment :: Plugins
Classifier: Intended Audience :: Science/Research
Classifier: Topic :: Scientific/Engineering :: Physics
Classifier: Natural Language :: English
License-File: LICENSE
License-File: AUTHORS
Requires-Dist: aiida-core (<2.0.0,>=1.3.0)
Requires-Dist: pyyaml
Provides-Extra: docs
Requires-Dist: docutils ; extra == 'docs'
Requires-Dist: sphinx ; extra == 'docs'
Requires-Dist: sphinxcontrib-contentui ; extra == 'docs'
Requires-Dist: sphinx-rtd-theme ; extra == 'docs'
Requires-Dist: sphinxcontrib-details-directive ; (python_version >= "3.0") and extra == 'docs'
Provides-Extra: pre-commit
Requires-Dist: pre-commit (>=2.6.0) ; extra == 'pre-commit'
Requires-Dist: yapf (==0.30.0) ; extra == 'pre-commit'
Requires-Dist: pylint (==2.5.2) ; extra == 'pre-commit'
Provides-Extra: testing
Requires-Dist: pytest (>=2.9) ; extra == 'testing'
Requires-Dist: pytest-timeout ; extra == 'testing'
Requires-Dist: pytest-cov (>=2.5.0) ; extra == 'testing'
Requires-Dist: pgtest ; extra == 'testing'
